{"otherData": {},"traceEvents":[{"cat":"function","dur":171366,"name":"glfwInit","ph":"X","pid":0,"tid":2335820379,"ts":103935972550},{"cat":"function","dur":176564,"name":"glfwCreateWindow","ph":"X","pid":0,"tid":2335820379,"ts":103936144038},{"cat":"function","dur":6264,"name":"void __cdecl Kablunk::OpenGLContext::Init(void)","ph":"X","pid":0,"tid":2335820379,"ts":103936320672},{"cat":"function","dur":355242,"name":"__cdecl Kablunk::WindowsWindow::WindowsWindow(const struct Kablunk::WindowProps &)","ph":"X","pid":0,"tid":2335820379,"ts":103935971854},{"cat":"function","dur":176,"name":"void __cdecl Kablunk::ImGuiLayer::OnAttach(void)","ph":"X","pid":0,"tid":2335820379,"ts":103936327157},{"cat":"function","dur":213,"name":"void __cdecl Kablunk::Application::PushOverlay(class Kablunk::Layer *)","ph":"X","pid":0,"tid":2335820379,"ts":103936327155},{"cat":"function","dur":21,"name":"__cdecl Kablunk::OpenGLVertexBuffer::OpenGLVertexBuffer(float *,unsigned int)","ph":"X","pid":0,"tid":2335820379,"ts":103936328167},{"cat":"function","dur":0,"name":"void __cdecl Kablunk::OpenGLVertexBuffer::Bind(void) const","ph":"X","pid":0,"tid":2335820379,"ts":103936328515},{"cat":"function","dur":22,"name":"__cdecl Kablunk::OpenGLIndexBuffer::OpenGLIndexBuffer(unsigned int *,unsigned int)","ph":"X","pid":0,"tid":2335820379,"ts":103936328562},{"cat":"function","dur":1,"name":"void __cdecl Kablunk::OpenGLIndexBuffer::Bind(void) const","ph":"X","pid":0,"tid":2335820379,"ts":103936328610},{"cat":"function","dur":22,"name":"__cdecl Kablunk::OpenGLTexture2D::OpenGLTexture2D(unsigned int,unsigned int)","ph":"X","pid":0,"tid":2335820379,"ts":103936328635},{"cat":"function","dur":7,"name":"void __cdecl Kablunk::OpenGLTexture2D::SetData(void *,unsigned int)","ph":"X","pid":0,"tid":2335820379,"ts":103936328688},{"cat":"function","dur":128,"name":"class std::basic_string<char,struct std::char_traits<char>,class std::allocator<char> > __cdecl Kablunk::OpenGLShader::ReadFile(const class std::basic_string<char,struct std::char_traits<char>,class std::allocator<char> > &)","ph":"X","pid":0,"tid":2335820379,"ts":103936328728},{"cat":"function","dur":43,"name":"class std::unordered_map<unsigned int,class std::basic_string<char,struct std::char_traits<char>,class std::allocator<char> >,struct std::hash<unsigned int>,struct std::equal_to<unsigned int>,class std::allocator<struct std::pair<unsigned int const ,class std::basic_string<char,struct std::char_traits<char>,class std::allocator<char> > > > > __cdecl Kablunk::OpenGLShader::PreProcess(const class std::basic_string<char,struct std::char_traits<char>,class std::allocator<char> > &)","ph":"X","pid":0,"tid":2335820379,"ts":103936328886},{"cat":"function","dur":586,"name":"void __cdecl Kablunk::OpenGLShader::Compile(const class std::unordered_map<unsigned int,class std::basic_string<char,struct std::char_traits<char>,class std::allocator<char> >,struct std::hash<unsigned int>,struct std::equal_to<unsigned int>,class std::allocator<struct std::pair<unsigned int const ,class std::basic_string<char,struct std::char_traits<char>,class std::allocator<char> > > > > &)","ph":"X","pid":0,"tid":2335820379,"ts":103936328955},{"cat":"function","dur":862,"name":"__cdecl Kablunk::OpenGLShader::OpenGLShader(const class std::basic_string<char,struct std::char_traits<char>,class std::allocator<char> > &)","ph":"X","pid":0,"tid":2335820379,"ts":103936328727},{"cat":"function","dur":2,"name":"void __cdecl Kablunk::OpenGLShader::Bind(void) const","ph":"X","pid":0,"tid":2335820379,"ts":103936329622},{"cat":"function","dur":22,"name":"void __cdecl Kablunk::OpenGLShader::SetInt(const class std::basic_string<char,struct std::char_traits<char>,class std::allocator<char> > &,int)","ph":"X","pid":0,"tid":2335820379,"ts":103936329647},{"cat":"function","dur":2291,"name":"void __cdecl Kablunk::Renderer2D::Init(void)","ph":"X","pid":0,"tid":2335820379,"ts":103936327401},{"cat":"function","dur":2322,"name":"void __cdecl Kablunk::Renderer::Init(void)","ph":"X","pid":0,"tid":2335820379,"ts":103936327390},{"cat":"function","dur":357889,"name":"__cdecl Kablunk::Application::Application(void)","ph":"X","pid":0,"tid":2335820379,"ts":103935971841},{"cat":"function","dur":4,"name":"__cdecl Kablunk::OrthographicCamera::OrthographicCamera(float,float,float,float)","ph":"X","pid":0,"tid":2335820379,"ts":103936329959},{"cat":"function","dur":7,"name":"void __cdecl Kablunk::Application::PushLayer(class Kablunk::Layer *)","ph":"X","pid":0,"tid":2335820379,"ts":103936329988}]}